README.md
setup.cfg
setup.py
detectvpn/__init__.py
detectvpn/main.py
detectvpn.egg-info/PKG-INFO
detectvpn.egg-info/SOURCES.txt
detectvpn.egg-info/dependency_links.txt
detectvpn.egg-info/top_level.txt